kestrel_kernels/__init__.py
kestrel_kernels/activation.cpython-310-x86_64-linux-gnu.so
kestrel_kernels/cutils.py
kestrel_kernels/fp8_quant.cpython-310-x86_64-linux-gnu.so
kestrel_kernels/fused_linear_residual.cpython-310-x86_64-linux-gnu.so
kestrel_kernels/fused_linear_residual_ops.py
kestrel_kernels/fused_mlp.cpython-310-x86_64-linux-gnu.so
kestrel_kernels/kv_cache_write.cpython-310-x86_64-linux-gnu.so
kestrel_kernels/layernorm_cuda.cpython-310-x86_64-linux-gnu.so
kestrel_kernels/moe_sum.cpython-310-x86_64-linux-gnu.so
kestrel_kernels/precompile.py
kestrel_kernels/rotary_embedding.cpython-310-x86_64-linux-gnu.so
kestrel_kernels/tau_tail.cpython-310-x86_64-linux-gnu.so
kestrel_kernels/tau_tail_ops.py
kestrel_kernels/configs/__init__.py
kestrel_kernels/configs/cute_moe_E64_H2048_I1024_bf16_sm90.json
kestrel_kernels/configs/cute_moe_E64_H2048_I1024_fp8_sm90.json
kestrel_kernels/cute_moe/__init__.py
kestrel_kernels/cute_moe/config.py
kestrel_kernels/cute_moe/dispatch.py
kestrel_kernels/cute_moe/utils.py
kestrel_kernels/flash_attn/__init__.py
kestrel_kernels/flash_attn/cute/__init__.py
kestrel_kernels/flash_attn/cute/block_sparsity.py
kestrel_kernels/flash_attn/cute/cute_dsl_utils.py
kestrel_kernels/flash_attn/cute/interface.py
kestrel_kernels/flash_attn/cute/mask_definitions.py
kestrel_kernels/flash_attn/cute/utils.py
kestrel_kernels/fp8_quant_cute/__init__.py
kestrel_kernels/fp8_quant_cute/dispatch.py
kestrel_kernels/gelu_residual/__init__.py
kestrel_kernels/gelu_residual/dispatch.py
kestrel_kernels/moe_align/__init__.py
kestrel_kernels/moe_align/dispatch.py
kestrel_kernels/precompiled/__init__.py
kestrel_kernels/precompiled/cute_moe_down_m128_n256_k128_N2048_K1024_w8_s2_wgmma_sm90.so
kestrel_kernels/precompiled/cute_moe_down_m128_n256_k128_N2048_K1024_w8_s2_wgmma_sm90a.so
kestrel_kernels/precompiled/cute_moe_down_m128_n256_k128_N2048_K1024_w8_s4_fp8_wgmma_pdl_sm90.so
kestrel_kernels-0.1.0.dist-info/METADATA
kestrel_kernels-0.1.0.dist-info/WHEEL
kestrel_kernels-0.1.0.dist-info/RECORD
