Metadata-Version: 2.1
Name: kestrel-kernels
Version: 0.1.0
Summary: CUDA kernel library for Kestrel
Requires-Python: >=3.10
Requires-Dist: nvidia-cutlass-dsl>=4.3.4
Requires-Dist: apache-tvm-ffi
Requires-Dist: torch-c-dlpack-ext
Requires-Dist: torch==2.9.1
Provides-Extra: dev
Requires-Dist: pytest>=7.0; extra == "dev"
Requires-Dist: triton>=3.0; extra == "dev"
